Workbook

Sheet Прайс-лист
B2: ПРАЙС-ЛИСТ НА ПРОГРАММНЫЙ КОМПЛЕКС «ПВ-СИСТЕМА»
B3: Проектирование вентиляции и водоснабжения горно-рудных предприятий · действует с 26.10.2026
A6: 1. Сведения о программном обеспечении
A7: Наименование ПО | B7: Программный комплекс «ПВ-Система»
A8: Правообладатель | B8: ООО «ПВ-Система»
A9: Класс ПО | B9: Средства инженерного проектирования и расчётов (CAD)
A10: Назначение | B10: Проектирование вентиляции и водоснабжения рудников
A11: Способ распространения | B11: Лицензионный ключ на рабочее место (ПК), передаётся в электронном виде
A12: Сайт программы | B12: пв-система.рф
A14: 2. Стоимость лицензий
A15: Наименование позиции | B15: Ед. изм. | C15: Кол-во рабочих мест | D15: Цена за рабочее место, ₽ | E15: Стоимость, ₽
A16: Лицензионный ключ «ПВ-Система» на одно рабочее место (ПК) | B16: лицензия | C16: 1 | D16: 240000 | E16: =C16*D16 -> 240000
A17: Дополнительное рабочее место к лицензии «ПВ-Система» (за каждый ПК) | B17: лицензия | C17: 1 | D17: 240000 | E17: =C17*D17 -> 240000
A18: Индивидуальная лицензия — расчёт по протяжённости сети горных выработок и коэффициенту сложности | B18: лицензия | C18: по расчёту | D18: — | E18: см. лист «Калькулятор»
A20: 3. В стоимость лицензии входит
A21: ✓ | B21: Установка и активация программного комплекса на рабочих местах заказчика
A22: ✓ | B22: Эксплуатационная документация пользователя на русском языке
A23: ✓ | B23: Техническая поддержка по телефону и электронной почте
A24: ✓ | B24: Обновления программного комплекса в течение срока действия лицензии
A26: 4. Условия
A27: • Цены указаны в российских рублях. НДС не облагается на основании подп. 26 п. 2 ст. 149 НК РФ (передача прав на ПО, включённое в Единый реестр российских программ).
A28: • Обучение пользователей (курс 40 академических часов) оплачивается отдельно по договорённости.
A29: • Лицензионный ключ передаётся в течение 3 рабочих дней после оплаты.
A30: • Окончательная стоимость индивидуальной лицензии фиксируется в коммерческом предложении и лицензионном договоре.
A31: • Скидка за количество рабочих мест: от 10 мест — 10%, от 15 мест — 20% (см. «Методика расчёта», табл. 3).
A33: ООО «ПВ-Система» · Республика Башкортостан, г. Сибай, ул. Куйбышева, д. 20
A34: Тел.: +7 (960) 392-42-55, +7 (933) 044-70-17 · pvsistema@mail.ru · пв-система.рф

Sheet Методика расчёта
B2: МЕТОДИКА РАСЧЁТА СТОИМОСТИ ЛИЦЕНЗИИ
B3: Индивидуальный расчёт по параметрам горного предприятия
A6: Формула расчёта
A7: Стоимость = Базовая стоимость × Kпр × Kсл × Количество рабочих мест × (1 − Скидка)
A8: • Базовая стоимость — 240 000 ₽ (лицензия на 1 рабочее место, сеть горных выработок до 50 км, категория сложности I).
A9: • Kпр — коэффициент протяжённости сети горных выработок (таблица 1).
A10: • Kсл — коэффициент сложности вентиляционной сети (таблица 2).
A11: • Количество рабочих мест — число компьютеров, на которых будет работать программа; Скидка — по количеству рабочих мест (таблица 3).
A13: Таблица 1. Коэффициент протяжённости сети горных выработок (Kпр)
A14: Протяжённость сети, км | B14: Описание | C14: От, км | D14: До, км | E14: Kпр
A15: до 50 км | B15: Небольшой рудник, один-два участка | C15: 0 | D15: 50 | E15: 1
A16: 50–100 км | B16: Средний рудник | C16: 50 | D16: 100 | E16: 1.3
A17: 100–200 км | B17: Крупный рудник | C17: 100 | D17: 200 | E17: 1.6
A18: 200–350 км | B18: Рудник с несколькими шахтными полями | C18: 200 | D18: 350 | E18: 2
A19: свыше 350 км | B19: Горно-обогатительный комбинат, объединённая сеть | C19: 350 | D19: — | E19: 2.5
A21: Таблица 2. Коэффициент сложности вентиляционной сети (Kсл)
A22: Категория сложности | B22: Характерные признаки сети | C22: Кол-во ветвей | D22: Вентиляторы главного проветривания | E22: Kсл
A23: I — простая | B23: Один горизонт, одна вентиляторная установка, без пожарно-оросительного трубопровода | C23: до 500 | D23: 1 | E23: 1
A24: II — средняя | B24: 2–3 горизонта, несколько стволов, пожарно-оросительный трубопровод | C24: 500–1 500 | D24: 1–2 | E24: 1.2
A25: III — сложная | B25: Многогоризонтная сеть, участковые вентиляторы, диагонали, естественная тяга | C25: 1 500–3 000 | D25: 2–3 | E25: 1.4
A26: IV — особо сложная | B26: Несколько шахтных полей, связанные сети, глубокие горизонты, повышенные требования ПЛА | C26: свыше 3 000 | D26: 4 и более | E26: 1.7
A28: Категория сложности определяется по совокупности признаков на основании схемы вентиляции рудника, предоставленной заказчиком. При несовпадении признаков принимается более высокая категория.
A30: Таблица 3. Скидка за количество рабочих мест
A31: Количество рабочих мест | B31: Описание | C31: От, мест | D31: До, мест | E31: Скидка
A32: 1–9 | B32: Стандартная цена | C32: 1 | D32: 9 | E32: 0
A33: 10–14 | B33: Крупное предприятие | C33: 10 | D33: 14 | E33: 0.1
A34: 15 и более | B34: Горно-обогатительный комбинат, группа рудников | C34: 15 | D34: — | E34: 0.2
A36: ООО «ПВ-Система» · Республика Башкортостан, г. Сибай, ул. Куйбышева, д. 20
A37: Тел.: +7 (960) 392-42-55, +7 (933) 044-70-17 · pvsistema@mail.ru · пв-система.рф

Sheet Калькулятор
B2: КАЛЬКУЛЯТОР СТОИМОСТИ ЛИЦЕНЗИИ
B3: Заполните поля, выделенные жёлтым — расчёт выполнится автоматически
A6: Исходные данные предприятия
A7: Наименование предприятия | B7: Рудник (пример)
A8: Протяжённость сети горных выработок, км | B8: 5 | C8: Суммарная длина выработок по схеме вентиляции
A9: Категория сложности сети | B9: I — простая | C9: Выбор из списка, см. «Методика расчёта», табл. 2
A10: Количество рабочих мест | B10: 1 | C10: Компьютеры, на которых будет работать программа
A12: Расчёт
A13: Показатель | B13: Значение
A14: Базовая стоимость (1 место, до 50 км, категория I) | B14: 240000
A15: Коэффициент протяжённости Kпр | B15: =LOOKUP(B8,'Методика расчёта'!$C$15:$C$19,'Методика расчёта'!$E$15:$E$19) -> 1
A16: Коэффициент сложности Kсл | B16: =VLOOKUP(B9,'Методика расчёта'!$A$23:$E$26,5,FALSE) -> 1
A17: Стоимость одного рабочего места (база × Kпр × Kсл) | B17: =B14*B15*B16 -> 240000
A18: Количество рабочих мест | B18: =B10 -> 1
A19: Стоимость без скидки (стоимость места × количество мест) | B19: =B17*B18 -> 240000
A20: Скидка за количество мест (табл. 3 методики) | B20: =LOOKUP(B10,'Методика расчёта'!$C$32:$C$34,'Методика расчёта'!$E$32:$E$34) -> 0
A21: ИТОГО СТОИМОСТЬ ЛИЦЕНЗИИ | B21: =B19*(1-B20) -> 240000
A22: Средняя стоимость одного рабочего места | B22: =B21/MAX(1,B10) -> 240000
A23: НДС | B23: не облагается (подп. 26 п. 2 ст. 149 НК РФ)
A25: Расчёт носит предварительный характер. Окончательная стоимость фиксируется в коммерческом предложении после анализа схемы вентиляции предприятия.
A27: ООО «ПВ-Система» · Республика Башкортостан, г. Сибай, ул. Куйбышева, д. 20
A28: Тел.: +7 (960) 392-42-55, +7 (933) 044-70-17 · pvsistema@mail.ru · пв-система.рф

Sheet Примеры расчёта
B2: ПРИМЕРЫ РАСЧЁТА ДЛЯ ТИПОВЫХ ПРЕДПРИЯТИЙ
B3: Иллюстрация применения методики · все значения рассчитываются формулами
A6: Типовые варианты лицензирования
A7: Тип предприятия | B7: Протяжённость, км | C7: Категория сложности | D7: Kпр | E7: Kсл | F7: Рабочих мест | G7: Скидка за места | H7: Итого, ₽
A8: Небольшой рудник | B8: 35 | C8: I — простая | D8: =LOOKUP(B8,'Методика расчёта'!$C$15:$C$19,'Методика расчёта'!$E$15:$E$19) -> 1 | E8: =VLOOKUP(C8,'Методика расчёта'!$A$23:$E$26,5,FALSE) -> 1 | F8: 5 | G8: =LOOKUP(F8,'Методика расчёта'!$C$32:$C$34,'Методика расчёта'!$E$32:$E$34) -> 0 | H8: =240000*D8*E8*F8*(1-G8) -> 1200000
A9: Средний рудник | B9: 80 | C9: II — средняя | D9: =LOOKUP(B9,'Методика расчёта'!$C$15:$C$19,'Методика расчёта'!$E$15:$E$19) -> 1.3 | E9: =VLOOKUP(C9,'Методика расчёта'!$A$23:$E$26,5,FALSE) -> 1.2 | F9: 5 | G9: =LOOKUP(F9,'Методика расчёта'!$C$32:$C$34,'Методика расчёта'!$E$32:$E$34) -> 0 | H9: =240000*D9*E9*F9*(1-G9) -> 1872000
A10: Крупный рудник | B10: 150 | C10: III — сложная | D10: =LOOKUP(B10,'Методика расчёта'!$C$15:$C$19,'Методика расчёта'!$E$15:$E$19) -> 1.6 | E10: =VLOOKUP(C10,'Методика расчёта'!$A$23:$E$26,5,FALSE) -> 1.4 | F10: 8 | G10: =LOOKUP(F10,'Методика расчёта'!$C$32:$C$34,'Методика расчёта'!$E$32:$E$34) -> 0 | H10: =240000*D10*E10*F10*(1-G10) -> 4300800
A11: Рудник с несколькими шахтными полями | B11: 280 | C11: III — сложная | D11: =LOOKUP(B11,'Методика расчёта'!$C$15:$C$19,'Методика расчёта'!$E$15:$E$19) -> 2 | E11: =VLOOKUP(C11,'Методика расчёта'!$A$23:$E$26,5,FALSE) -> 1.4 | F11: 10 | G11: =LOOKUP(F11,'Методика расчёта'!$C$32:$C$34,'Методика расчёта'!$E$32:$E$34) -> 0.1 | H11: =240000*D11*E11*F11*(1-G11) -> 6048000
A12: Горно-обогатительный комбинат | B12: 420 | C12: IV — особо сложная | D12: =LOOKUP(B12,'Методика расчёта'!$C$15:$C$19,'Методика расчёта'!$E$15:$E$19) -> 2.5 | E12: =VLOOKUP(C12,'Методика расчёта'!$A$23:$E$26,5,FALSE) -> 1.7 | F12: 15 | G12: =LOOKUP(F12,'Методика расчёта'!$C$32:$C$34,'Методика расчёта'!$E$32:$E$34) -> 0.2 | H12: =240000*D12*E12*F12*(1-G12) -> 12240000
A14: Сравнение: стандартные позиции прайс-листа
A15: Вариант (без коэффициентов, сеть до 50 км, категория I) | F15: Рабочих мест | G15: Цена за место со скидкой, ₽ | H15: Итого, ₽
A16: Лицензия на 1 рабочее место | F16: 1 | G16: =H16/F16 -> 240000 | H16: =F16*240000*(1-LOOKUP(F16,'Методика расчёта'!$C$32:$C$34,'Методика расчёта'!$E$32:$E$34)) -> 240000
A17: Лицензии на 5 рабочих мест | F17: 5 | G17: =H17/F17 -> 240000 | H17: =F17*240000*(1-LOOKUP(F17,'Методика расчёта'!$C$32:$C$34,'Методика расчёта'!$E$32:$E$34)) -> 1200000
A18: Лицензии на 10 рабочих мест (скидка 10%) | F18: 10 | G18: =H18/F18 -> 216000 | H18: =F18*240000*(1-LOOKUP(F18,'Методика расчёта'!$C$32:$C$34,'Методика расчёта'!$E$32:$E$34)) -> 2160000
A19: Лицензии на 15 рабочих мест (скидка 20%) | F19: 15 | G19: =H19/F19 -> 192000 | H19: =F19*240000*(1-LOOKUP(F19,'Методика расчёта'!$C$32:$C$34,'Методика расчёта'!$E$32:$E$34)) -> 2880000
A21: Примеры приведены для иллюстрации методики и не являются публичной офертой.
A23: ООО «ПВ-Система» · Республика Башкортостан, г. Сибай, ул. Куйбышева, д. 20
A24: Тел.: +7 (960) 392-42-55, +7 (933) 044-70-17 · pvsistema@mail.ru · пв-система.рф
